Metadata-Version: 2.1
Name: workflux
Version: 0.5.0
Summary: A platform-agnostic, cloud-ready framework for simplified deployment of the Common Workflow Language using a graphical web interface
Home-page: https://github.com/CompEpigen/workflUX
Author: Kersten Henrik Breuer
Author-email: k.breuer@dkfz.de
License: Apache 2.0
Download-URL: https://github.com/CompEpigen/workflUX
Platform: UNKNOWN
Classifier: Development Status :: 4 - Beta
Classifier: Intended Audience :: Developers
Classifier: Intended Audience :: Science/Research
Classifier: License :: OSI Approved :: Apache Software License
Classifier: Natural Language :: English
Classifier: Operating System :: POSIX
Classifier: Operating System :: POSIX :: Linux
Classifier: Operating System :: MacOS :: MacOS X
Classifier: Operating System :: OS Independent
Classifier: Operating System :: Microsoft :: Windows
Classifier: Operating System :: Microsoft :: Windows :: Windows 10
Classifier: Operating System :: Microsoft :: Windows :: Windows 8.1
Classifier: Programming Language :: Python :: 3.5
Classifier: Programming Language :: Python :: 3.6
Classifier: Programming Language :: Python :: 3.7
Classifier: Topic :: Scientific/Engineering
Classifier: Topic :: Scientific/Engineering :: Bio-Informatics
Classifier: Topic :: Scientific/Engineering :: Information Analysis
Classifier: Topic :: Scientific/Engineering :: Medical Science Apps.
Classifier: Topic :: System :: Distributed Computing
License-File: LICENSE
Requires-Dist: werkzeug
Requires-Dist: flask
Requires-Dist: flask-wtf
Requires-Dist: flask-login
Requires-Dist: flask-sqlalchemy
Requires-Dist: pyexcel
Requires-Dist: pyexcel-io
Requires-Dist: pyexcel-ods
Requires-Dist: pyexcel-ods3
Requires-Dist: pyexcel-xls
Requires-Dist: pyexcel-xlsx (<=0.5.7)
Requires-Dist: PyYAML (>=5.1)
Requires-Dist: pexpect
Requires-Dist: janis-pipelines
Requires-Dist: cwltool (==3.0.20201203173111)
Requires-Dist: psutil
Requires-Dist: miniwdl (>=0.0.5)
Requires-Dist: requests
Requires-Dist: path (<13.2.0)
Requires-Dist: schema-salad (>=7.0.20200811075006)
Requires-Dist: trs-cli (>=0.3.1)
Requires-Dist: pydantic
Requires-Dist: cwlformat (<=2020.5.19)
Provides-Extra: testing
Requires-Dist: pytest ; extra == 'testing'
